README.rst
setup.py
csgo/__init__.py
csgo/client.py
csgo/common_enums.py
csgo/enums.py
csgo/msg.py
csgo/proto_enums.py
csgo/sharecode.py
csgo.egg-info/PKG-INFO
csgo.egg-info/SOURCES.txt
csgo.egg-info/dependency_links.txt
csgo.egg-info/requires.txt
csgo.egg-info/top_level.txt
csgo.egg-info/zip-safe
csgo/features/__init__.py
csgo/features/items.py
csgo/features/match.py
csgo/features/player.py
csgo/features/sharedobjects.py
csgo/protobufs/__init__.py
csgo/protobufs/base_gcmessages_pb2.py
csgo/protobufs/cstrike15_gcmessages_pb2.py
csgo/protobufs/econ_gcmessages_pb2.py
csgo/protobufs/engine_gcmessages_pb2.py
csgo/protobufs/gcsdk_gcmessages_pb2.py
csgo/protobufs/gcsystemmsgs_pb2.py
csgo/protobufs/steammessages_pb2.py